Metadata-Version: 1.1
Name: aurabot
Version: 0.0.1
Summary: A very basic Fortnite Bot
Home-page: UNKNOWN
Author: FireGlitches
Author-email: FireGlitches@protonmail.com
License: MIT
Keywords: fortnite
Platform: UNKNOWN
Classifier: Development Status :: 5 - Production/Stable
Classifier: Intended Audience :: Education
Classifier: Operating System :: Microsoft :: Windows :: Windows 10
Classifier: License :: OSI Approved :: MIT License
Classifier: Programming Language :: Python :: 3
